
{
  "image_slider": [
    {
      "title": "Daily Prayer session",
      "url": "https://raw.githubusercontent.com/WebDeveloper-ygt/bems_public/master/IMG-20190905-WA0085.jpg"
    },
    {
      "title": "Visit to Dharwad Regional Science Center",
      "url": "https://raw.githubusercontent.com/WebDeveloper-ygt/bems_public/master/IMG-20191124-WA0025.jpg"
    },
    {
      "title": "New School Buildings",
      "url": "https://raw.githubusercontent.com/WebDeveloper-ygt/bems_public/master/IMG_03101.jpg"
    }
  ],
  "notices": [
    {
      "title": "Covid19 Classes suspended",
      "description": "All the classes are suspended due to Corona pandemic, untill then please stay home stay safe"
    },
    {
      "title": "Admissions are opened",
      "description": "Adminssions to the all standards are opened, feel free to contact us or visit school"
    }
  ],
  "content": [
    {
      "title": "Mission",
      "description": "To make world better place"
    },
    {
      "title": "History",
      "description" : "School started in the year of 2015"
    },
    {
      "title" : "Aim",
      "description" : "We are on top of our priorities, We always aim at the students development"
    }
   ]
}
